LICENSE.txt
MANIFEST.in
setup.py
assets/colorgrid.png
assets/grid3D.mtl
assets/grid3D.obj
assets/primitives.mtl
assets/primitives.obj
assets/uvgrid.png
assets/white.png
docs/_static/finalvr_composite3_small.png
docs/_static/primitives.png
docs/_static/shading_example.png
docs/_static/tut1_blank_window.png
docs/_static/tut1_gray_monkey.png
docs/_static/tut2_final.png
docs/_static/tut3_blue_torus.png
docs/_static/tut3_gray_torus.png
docs/_static/tut3_red_torus.png
fruitloop/__init__.py
fruitloop/camera.py
fruitloop/collision.py
fruitloop/fbo.py
fruitloop/light.py
fruitloop/materials.py
fruitloop/mesh.py
fruitloop/physical.py
fruitloop/resources.py
fruitloop/scene.py
fruitloop/shader.py
fruitloop/texture.py
fruitloop/wavefront.py
fruitloop.egg-info/PKG-INFO
fruitloop.egg-info/SOURCES.txt
fruitloop.egg-info/dependency_links.txt
fruitloop.egg-info/requires.txt
fruitloop.egg-info/top_level.txt
fruitloop/utils/__init__.py
fruitloop/utils/coordinates.py
fruitloop/utils/gl.py
fruitloop/utils/mixins.py
fruitloop/utils/observers.py
fruitloop/utils/scenegraph.py
fruitloop/utils/vertices.py
shaders/basicDeferred.frag
shaders/basicDeferred.vert
shaders/combShader.frag
shaders/combShader.vert
shaders/shadowShader.frag
shaders/shadowShader.vert
tests/__init__.py
tests/run.py
tests/test_meshes.py
tests/test_physical.py
third_party/transformations.c