Metadata-Version: 1.1
Name: fruitloop
Version: 0.6
Summary: 3D Graphics Engine for CAVE VR setups
Home-page: https://www.github.com/neuroneuro15/fruitloop
Author: Nicholas A. Del Grosso
Author-email: delgrosso.nick@gmail.com
License: MIT
Keywords: graphics 3D pyglet psychopy python virtual reality VR
Platform: UNKNOWN
Classifier: Topic :: Multimedia :: Graphics :: 3D Rendering
Classifier: Development Status :: 3 - Alpha
Classifier: License :: OSI Approved :: MIT License
Classifier: Intended Audience :: Science/Research
Classifier: Programming Language :: Python
Classifier: Programming Language :: Python :: 2
Classifier: Programming Language :: Python :: 2.7
Classifier: Programming Language :: Python :: 3
Classifier: Programming Language :: Python :: 3.3
Classifier: Programming Language :: Python :: 3.4
Classifier: Programming Language :: Python :: 3.5
Classifier: Programming Language :: Python :: 3.6
